[{"method":"POST","url":"/bugreporter","body":{"issue":{"project_id":61,"subject":"a bug report","description":"this is the message body from a bug report\n\nThis report has been brought to you by: \nHandle: mister_b\nName: Richard Belding\nEmail: belding@bayside.com\nViewing: http://web.pinwheelapi.local/calendar/2015/3/4\nUser Agent: Mozilla/5.0 (Macintosh; Intel Mac OS X 10_10_2) AppleWebKit/537.36 (KHTML, like Gecko) Chrome/40.0.2214.115 Safari/537.36\nSubscribed to orgs: [\"org_1\"]\nActing as: org_1\n\nUser Info:\n{\"user_id\":\"user_201412041437240x85341200x8460742\",\"user_handle\":\"mister_b\",\"email\":\"belding@bayside.com\",\"first_name\":\"Richard\",\"last_name\":\"Belding\",\"password\":null,\"timezone\":\"America/New_York\",\"ical_token\":\"50ea4ff3cf785ce6f8cf8a180174f5b26d657ba6\",\"active\":\"1\",\"last_modified\":\"2014-12-04 19:37:24\",\"version\":\"0\",\"settings\":{\"default_calendar\":\"\",\"start_of_day\":\"08:00:00\",\"end_of_day\":\"17:00:00\",\"DB_version\":\"0\",\"calendar_drawer_visible\":true,\"task_drawer_visible\":true,\"acting_org\":\"org_1\",\"all_org_display_text\":\"mister_b\",\"all_org_color\":null,\"always_advanced_entry\":false,\"summary_days\":null,\"summary_time\":null,\"summary_duration\":null},\"clever_id\":null,\"orgs\":[\"org_1\"],\"permissions\":[{\"message_calendar_subscribers\":true,\"org_id\":\"org_1\",\"org_name\":\"Bayside Tigers\",\"modify_handbook\":true,\"modify_theme\":true,\"view_hallpass_history\":true,\"view_admin_settings\":true,\"issue_hall_pass\":true,\"check_in_hall_pass\":true,\"org_wide_messaging\":true,\"modify_org_admins\":true,\"facilities_admin\":true,\"facilities_reserver\":true,\"create_public_calendars\":true,\"view_org_users\":true,\"create_unlisted_public_calendars\":true}],\"$promise\":{},\"$resolved\":true}\n\nLogger history:"}},"headers":{"host":"192.168.66.3:3000","accept":"*/*","content-type":"application/json","content-length":"1788","expect":"100-continue"},"query_string":{}},{"method":"POST","url":"/bugreporter","body":{"issue":{"project_id":61,"subject":"a second bug report","description":"another body to go with it\n\nThis report has been brought to you by: \nHandle: mister_b\nName: Richard Belding\nEmail: belding@bayside.com\nViewing: http://web.pinwheelapi.local/calendar/2015/3/4\nUser Agent: Mozilla/5.0 (Macintosh; Intel Mac OS X 10_10_2) AppleWebKit/537.36 (KHTML, like Gecko) Chrome/40.0.2214.115 Safari/537.36\nSubscribed to orgs: [\"org_1\"]\nActing as: org_1\n\nUser Info:\n{\"user_id\":\"user_201412041437240x85341200x8460742\",\"user_handle\":\"mister_b\",\"email\":\"belding@bayside.com\",\"first_name\":\"Richard\",\"last_name\":\"Belding\",\"password\":null,\"timezone\":\"America/New_York\",\"ical_token\":\"50ea4ff3cf785ce6f8cf8a180174f5b26d657ba6\",\"active\":\"1\",\"last_modified\":\"2014-12-04 19:37:24\",\"version\":\"0\",\"settings\":{\"default_calendar\":\"\",\"start_of_day\":\"08:00:00\",\"end_of_day\":\"17:00:00\",\"DB_version\":\"0\",\"calendar_drawer_visible\":true,\"task_drawer_visible\":true,\"acting_org\":\"org_1\",\"all_org_display_text\":\"mister_b\",\"all_org_color\":null,\"always_advanced_entry\":false,\"summary_days\":null,\"summary_time\":null,\"summary_duration\":null},\"clever_id\":null,\"orgs\":[\"org_1\"],\"permissions\":[{\"message_calendar_subscribers\":true,\"org_id\":\"org_1\",\"org_name\":\"Bayside Tigers\",\"modify_handbook\":true,\"modify_theme\":true,\"view_hallpass_history\":true,\"view_admin_settings\":true,\"issue_hall_pass\":true,\"check_in_hall_pass\":true,\"org_wide_messaging\":true,\"modify_org_admins\":true,\"facilities_admin\":true,\"facilities_reserver\":true,\"create_public_calendars\":true,\"view_org_users\":true,\"create_unlisted_public_calendars\":true}],\"$promise\":{},\"$resolved\":true}\n\nLogger history:"}},"headers":{"host":"192.168.66.3:3000","accept":"*/*","content-type":"application/json","content-length":"1779","expect":"100-continue"},"query_string":{}},{"method":"PUT","url":"/preppy/event","body":{"modTs":1425506324,"events":[{"id":"event_201503041658340x99811300x4844741","objType":"event","title":"history midterm","startTime":"1426798800","endTime":"1426802400","calendarId":"calendar_201412041502090x84687200x6773514","calendarName":"History","start_offset":-14400,"end_offset":-14400,"org_name":"Bayside Tigers"}]},"headers":{"host":"192.168.66.3:3000","content-type":"application/json","content-length":"323"},"query_string":{}},{"method":"POST","url":"/preppy/eventReminder","body":{"modTs":1425506334,"type":"relative","leadTime":7200,"reminderId":"reminder_pref_201503041658540x23764300x6927584","user":"user_201412041437240x85341200x8460742","events":[{"id":"event_201503041658290x10671800x9941533","objType":"event","title":"A history assignment","startTime":"1425934800","endTime":"1425938400","calendarId":"calendar_201412041502090x84687200x6773514","calendarName":"History","start_offset":-14400,"end_offset":-14400,"org_name":"Bayside Tigers"},{"id":"event_201503041658340x99811300x4844741","objType":"event","title":"history midterm","startTime":"1426798800","endTime":"1426802400","calendarId":"calendar_201412041502090x84687200x6773514","calendarName":"History","start_offset":-14400,"end_offset":-14400,"org_name":"Bayside Tigers"}]},"headers":{"host":"192.168.66.3:3000","content-type":"application/json","content-length":"763"},"query_string":{}},{"method":"PUT","url":"/preppy/calendar","body":{"calendarId":"calendar_201412041502090x84687200x6773514","events":[{"id":"event_201503041658290x10671800x9941533","objType":"event","title":"A history assignment","startTime":"1425934800","endTime":"1425938400","calendarId":"calendar_201412041502090x84687200x6773514","calendarName":"History","start_offset":-14400,"end_offset":-14400,"org_name":"Bayside Tigers"},{"id":"event_201503041658340x99811300x4844741","objType":"event","title":"history midterm","startTime":"1426798800","endTime":"1426802400","calendarId":"calendar_201412041502090x84687200x6773514","calendarName":"History","start_offset":-14400,"end_offset":-14400,"org_name":"Bayside Tigers"}],"calendarName":"History","user":"user_201412041437240x85341200x8460742"},"headers":{"host":"192.168.66.3:3000","content-type":"application/json","content-length":"730"},"query_string":{}},{"method":"POST","url":"/preppy/eventReminder","body":{"modTs":1425506367,"type":"relative","leadTime":7200,"reminderId":"reminder_pref_201503041659270x26316100x9934529","user":"user_201412041437240x85341200x8460742","events":[{"repeat_id":"event_201503041659270x24431400x2950372","id":"event_201503041659270x24431400x295037214265396001426543200","objType":"event","title":"repeating event test","startTime":"1426539600","endTime":"1426543200","calendarId":"calendar_201412041501370x35043600x4968436","calendarName":"Physics","start_offset":-14400,"end_offset":-14400,"org_name":"Bayside Tigers"}]},"headers":{"host":"192.168.66.3:3000","content-type":"application/json","content-length":"544"},"query_string":{}},{"method":"POST","url":"/preppy/eventReminder","body":{"modTs":1425506382,"type":"relative","leadTime":7200,"reminderId":"reminder_pref_201503041658540x23764300x6927584","user":"user_201412041437240x85341200x8460742","events":[{"id":"event_201503041659420x11405500x8129569","objType":"event","title":"another history event","startTime":"1427749200","endTime":"1427752800","calendarId":"calendar_201412041502090x84687200x6773514","calendarName":"History","start_offset":-14400,"end_offset":-14400,"org_name":"Bayside Tigers"}]},"headers":{"host":"192.168.66.3:3000","content-type":"application/json","content-length":"472"},"query_string":{}},{"method":"POST","url":"/mrpostman","body":{"type":"email","destination":["belding@bayside.com","mrs_culpepper@bayside.edu","mr_dewey@bayside.com","dr_mertz@bayside.com","zmorris@bayside.com","kkapowski@bayside.com","spowers@bayside.com"],"subject":"a message to the entire school","plainBody":"everything is open. Enjoy learning","htmlBody":"<!DOCTYPE html PUBLIC '-//W3C//DTD HTML 4.01 Transitional//EN'\n   'http://www.w3.org/TR/html4/loose.dtd'>\n<html width='100%' height='100%' style='width:100%!important;height:100%!important;'>\n  <head>\n    <meta http-equiv='X-UA-Compatible' content='IE=edge' />\n    <meta name='viewport' content='width=device-width, initial-scale = 1.0, maximum-scale = 1.0' />\n    <meta http-equiv='Content-Type' content='text/html; charset=utf-8' />\n    <meta name='apple-mobile-web-app-capable' content='yes' />\n    <meta name='apple-mobile-web-app-status-bar-style' content='black' />\n    <meta name='format-detection' content='telephone=no' />\n    <title>a message to the entire school</title>\n  </head>\n  <body width='100%' height='100%' style='width:100%!important;height:100%!important;-webkit-text-size-adjust:none;-ms-text-size-adjust:none;'>\n    <table align='center' cellspacing='0' cellpadding='0' border='0' width='100%' height='100%' bgcolor='#EEEEEE' style='margin:0;padding:0;border:0;width:100%!important;height:100%!important;'>\n      <tr>\n        <td align='center' valign='top' style='text-align: center; padding: 20px 0 50px'>\n          <center>\n            <table cellspacing='0' cellpadding='0' border='0' width='550px' style='text-align:left;padding:0;margin:0 auto;border:0;width:550px;font-family:verdana,arial,san-serif;font-size:14px;'>\n            <tr>\n              <td align='left' width='250px' height='102px' style='width:250px;height:102px;text-align:left;padding:0 30px 0;'><a href='http://web.pinwheelapi.local' target='_blank'><img src='http://web.pinwheelapi.local/assets/images/email-logo-dark.png' alt='Pinwheel' width='94px' height='76px' border='0' style='display:inline-block;border: 0;width:94px;height:76px;' /></a></td>\n\t\t\t\t\t\t\t<td  align='right' width='300px' style='text-align:right;width:300px;padding:0 30px 0;'><a style='color:#222222;font-weight:bold;'>March 4, 2015</a></td>\n\t\t\t\t\t\t</tr>\n\t\t\t\t\t\t<tr>\n              <td colspan='2' style='padding-top:30px;'>\n                <p height='1px' style='border-top:1px solid #dddddd;padding:0;margin:0;height:1px;max-height:1px;font-size:0;'>&nbsp;</p>\n              </td>\n            </tr>\n            <tr>\n              <td colspan='2' bgcolor='#F1F1F1' height='50px' style='height:50px;padding:0 30px;'><span style='display:inline-block;line-height: 50px;color:#222222;font-size:16px;'>a message to the entire school</span></td>\n            </tr>\n            <tr>\n              <td colspan='2'>\n                <p height='1px' style='border-top:1px solid #dddddd;padding:0;margin:0;height:1px;max-height:1px;font-size:0;'>&nbsp;</p>\n              </td>\n            </tr>\n\t\t\t\t\t\t<tr>\n\t\t\t\t\t\t\t<td colspan='2' width='550px' style='width:550px;word-break:break-word;word-wrap: break-word;padding:15px 30px 15px;table-layout: fixed;'>\n\t\t\t\t\t\t\t\t<p><strong>To:</strong> <em>Bayside Tigers</em>\n                <p>everything is open. Enjoy learning</p>\n\t\t\t\t\t\t\t</td>\n\t\t\t\t\t\t</tr>\n            <tr>\n              <td colspan='2' height='120px' style='height:120px;color:#8a898f;font-size:11px;padding:30px;'>\n                <p>Please do not reply to this message; it was sent from an unmonitored email address. This message is a service email related to your Pinwheel&reg; account.</p>\n              </td>\n            </tr>\n          </table>\n          </center>\n        </td>\n      </tr>\n    </table>\n  </body>\n</html>","displayName":"Pinwheel"},"headers":{"host":"192.168.66.3:3000","accept":"*/*","content-type":"application/json","content-length":"3873","expect":"100-continue"},"query_string":{}},{"method":"POST","url":"/mrpostman","body":{"type":"email","destination":["belding@bayside.com","kkapowski@bayside.com","spowers@bayside.com"],"subject":"don't forget your permission slips","plainBody":"the field trip is coming up and they are required","htmlBody":"<!DOCTYPE html PUBLIC '-//W3C//DTD HTML 4.01 Transitional//EN'\n   'http://www.w3.org/TR/html4/loose.dtd'>\n<html width='100%' height='100%' style='width:100%!important;height:100%!important;'>\n  <head>\n    <meta http-equiv='X-UA-Compatible' content='IE=edge' />\n    <meta name='viewport' content='width=device-width, initial-scale = 1.0, maximum-scale = 1.0' />\n    <meta http-equiv='Content-Type' content='text/html; charset=utf-8' />\n    <meta name='apple-mobile-web-app-capable' content='yes' />\n    <meta name='apple-mobile-web-app-status-bar-style' content='black' />\n    <meta name='format-detection' content='telephone=no' />\n    <title>don't forget your permission slips</title>\n  </head>\n  <body width='100%' height='100%' style='width:100%!important;height:100%!important;-webkit-text-size-adjust:none;-ms-text-size-adjust:none;'>\n    <table align='center' cellspacing='0' cellpadding='0' border='0' width='100%' height='100%' bgcolor='#EEEEEE' style='margin:0;padding:0;border:0;width:100%!important;height:100%!important;'>\n      <tr>\n        <td align='center' valign='top' style='text-align: center; padding: 20px 0 50px'>\n          <center>\n            <table cellspacing='0' cellpadding='0' border='0' width='550px' style='text-align:left;padding:0;margin:0 auto;border:0;width:550px;font-family:verdana,arial,san-serif;font-size:14px;'>\n            <tr>\n              <td align='left' width='250px' height='102px' style='width:250px;height:102px;text-align:left;padding:0 30px 0;'><a href='http://web.pinwheelapi.local' target='_blank'><img src='http://web.pinwheelapi.local/assets/images/email-logo-dark.png' alt='Pinwheel' width='94px' height='76px' border='0' style='display:inline-block;border: 0;width:94px;height:76px;' /></a></td>\n\t\t\t\t\t\t\t<td  align='right' width='300px' style='text-align:right;width:300px;padding:0 30px 0;'><a style='color:#222222;font-weight:bold;'>March 4, 2015</a></td>\n\t\t\t\t\t\t</tr>\n\t\t\t\t\t\t<tr>\n              <td colspan='2' style='padding-top:30px;'>\n                <p height='1px' style='border-top:1px solid #dddddd;padding:0;margin:0;height:1px;max-height:1px;font-size:0;'>&nbsp;</p>\n              </td>\n            </tr>\n            <tr>\n              <td colspan='2' bgcolor='#F1F1F1' height='50px' style='height:50px;padding:0 30px;'><span style='display:inline-block;line-height: 50px;color:#222222;font-size:16px;'>don't forget your permission slips</span></td>\n            </tr>\n            <tr>\n              <td colspan='2'>\n                <p height='1px' style='border-top:1px solid #dddddd;padding:0;margin:0;height:1px;max-height:1px;font-size:0;'>&nbsp;</p>\n              </td>\n            </tr>\n\t\t\t\t\t\t<tr>\n\t\t\t\t\t\t\t<td colspan='2' width='550px' style='width:550px;word-break:break-word;word-wrap: break-word;padding:15px 30px 15px;table-layout: fixed;'>\n\t\t\t\t\t\t\t\t<p><strong>To:</strong> <em>Physics</em>\n                <p>the field trip is coming up and they are required</p>\n\t\t\t\t\t\t\t</td>\n\t\t\t\t\t\t</tr>\n            <tr>\n              <td colspan='2' height='120px' style='height:120px;color:#8a898f;font-size:11px;padding:30px;'>\n                <p>Please do not reply to this message; it was sent from an unmonitored email address. This message is a service email related to your Pinwheel&reg; account.</p>\n              </td>\n            </tr>\n          </table>\n          </center>\n        </td>\n      </tr>\n    </table>\n  </body>\n</html>","displayName":"Pinwheel"},"headers":{"host":"192.168.66.3:3000","accept":"*/*","content-type":"application/json","content-length":"3812","expect":"100-continue"},"query_string":{}}]